{
	"wallpapers": [
		{
			"name": "1",
			"author": "Rutwik Patel",
			"url": "http://i.imgur.com/1q3CPmi.jpg",
			"dimensions": "566 x 566",
			"copyright": "Copyright , 2016 Rutwik Patel. All rights reserved."
		},
		{
			"name": "2",
			"author": "Rutwik Patel",
			"url": "http://i.imgur.com/h96UP2R.jpg",
			"dimensions": "318 x 565",
			"copyright": "Copyright , 2016 Rutwik Patel. All rights reserved."
		},
		{
			"name": "3",
			"author": "Rutwik Patel",
			"url": "http://i.imgur.com/Nc53O6b.png",
			"dimensions": "319 x 566",
			"copyright": "Copyright , 2016 Rutwik Patel. All rights reserved."
		},
		{
			"name": "4",
			"author": "Rutwik Patel",
			"url": "http://i.imgur.com/q2L1a34.jpg",
			"dimensions": "318 x 565",
			"copyright": "Copyright , 2016 Rutwik Patel. All rights reserved."
		},
		{
			"name": "5",
			"author": "Rutwik Patel",
			"url": "http://i.imgur.com/YPr5F5T.png",
			"dimensions": "319 x 566",
			"copyright": "Copyright , 2016 Rutwik Patel. All rights reserved."
		},
		{
			"name": "6",
			"author": "Rutwik Patel",
			"url": "http://i.imgur.com/opUCbQb.jpg",
			"dimensions": "318 x 565",
			"copyright": "Copyright , 2016 Rutwik Patel. All rights reserved."
		},
		{
			"name": "7",
			"author": "Rutwik Patel",
			"url": "http://i.imgur.com/OIXb4Ae.png",
			"dimensions": "319 x 566",
			"copyright": "Copyright , 2016 Rutwik Patel. All rights reserved."
		},
		{
			"name": "8",
			"author": "Rutwik Patel",
			"url": "http://i.imgur.com/JxK7aqs.jpg",
			"dimensions": "318 x 565",
			"copyright": "Copyright , 2016 Rutwik Patel. All rights reserved."
		},
		{
			"name": "9",
			"author": "Rutwik Patel",
			"url": "http://i.imgur.com/fT0FOn9.jpg",
			"dimensions": "340 x 566",
			"copyright": "Copyright , 2016 Rutwik Patel. All rights reserved."
		},
		{
			"name": "10",
			"author": "Rutwik Patel",
			"url": "http://i.imgur.com/cb5AKe8.jpg",
			"dimensions": "319 x 566",
			"copyright": "Copyright , 2016 Rutwik Patel. All rights reserved."
		}
		
	]
}
